sds/__init__.py
sds/sds.py
sds-0.1.dist-info/.gitignore
sds-0.1.dist-info/DESCRIPTION.rst
sds-0.1.dist-info/METADATA
sds-0.1.dist-info/RECORD
sds-0.1.dist-info/WHEEL
sds-0.1.dist-info/metadata.json
sds-0.1.dist-info/top_level.txt
