Metadata-Version: 2.0
Name: sds
Version: 0.1
Summary: Stochastic Diffusion Search
Home-page: http://www.aomartin.co.uk/
Author: Andrew Owen Martin
Author-email: a.martin@gold.ac.uk
License: UNKNOWN
Keywords: swarm,artificial,intelligence,search
Platform: UNKNOWN
Classifier: Development Status :: 3 - Alpha
Classifier: Intended Audience :: Developers
Classifier: Intended Audience :: Science/Research
Classifier: License :: OSI Approved :: Apache Software License
Classifier: Operating System :: OS Independent
Classifier: Programming Language :: Python :: 3
Classifier: Programming Language :: Python
Classifier: Topic :: Scientific/Engineering :: Artificial Intelligence
